yealinkManager/ConstantsYealinkManager.py
yealinkManager/YealinkManager.py
yealinkManager/__init__.py
YealinkManager-2.1.dist-info/METADATA
YealinkManager-2.1.dist-info/WHEEL
YealinkManager-2.1.dist-info/entry_points.txt
YealinkManager-2.1.dist-info/top_level.txt
YealinkManager-2.1.dist-info/RECORD
