Metadata-Version: 2.1
Name: YealinkManager
Version: 2.1
Summary: Automate Action Uri in yealinkPhone
Home-page: UNKNOWN
Author: Giacomo Giusti
Author-email: giacomino.giusti@gmail.com
License: UNKNOWN
Platform: UNKNOWN
Requires-Python: >3.6.0
Requires-Dist: requests
